setup.py
advisor_areeh_fork.egg-info/PKG-INFO
advisor_areeh_fork.egg-info/SOURCES.txt
advisor_areeh_fork.egg-info/dependency_links.txt
advisor_areeh_fork.egg-info/entry_points.txt
advisor_areeh_fork.egg-info/not-zip-safe
advisor_areeh_fork.egg-info/requires.txt
advisor_areeh_fork.egg-info/top_level.txt
advisor_client/__init__.py
advisor_client/client.py
advisor_client/model.py
advisor_client/commandline/__init__.py
advisor_client/commandline/admin_command.py
advisor_client/commandline/command.py
advisor_client/runner/__init__.py
advisor_client/runner/abstract_runner.py
advisor_client/runner/local_runner.py
advisor_client/runner/local_runner_test.py
advisor_client/runner/runner_launcher.py