Metadata-Version: 1.0
Name: advisor-areeh-fork
Version: 0.1.6
Summary: Advisor is the hyper parameters tuning system for black box optimization
Home-page: https://github.com/areeh/advisor
Author: areeh
Author-email: arehaartveit@gmail.com
License: UNKNOWN
Platform: UNKNOWN
